LICENSE.txt
MANIFEST.in
README.html
README.pdf
README.txt
eo2int
eonums.py
ez_setup.py
int2eo
setup.cfg
setup.py
eonums.egg-info/PKG-INFO
eonums.egg-info/SOURCES.txt
eonums.egg-info/dependency_links.txt
eonums.egg-info/top_level.txt