Metadata-Version: 1.0
Name: eonums
Version: 0.9.0
Summary: A module for converting between integer numbers and Esperanto strings.
Home-page: http://www.dinu-gherman.net/
Author: Dinu Gherman
Author-email: gherman@darwin.in-berlin.de
License: GNU General Public Licence v3 (GPLv3)
Download-URL: http://www.dinu-gherman.net/tmp/eonums-0.9.0.tar.gz
Keywords: number,conversion,Esperanto
Platform: Posix
Platform: Windows
Classifier: Development Status :: 4 - Beta
Classifier: Environment :: Console
Classifier: Intended Audience :: Developers
Classifier: Intended Audience :: End Users/Desktop
Classifier: Intended Audience :: Education
Classifier: License :: OSI Approved :: GNU General Public License (GPL)
Classifier: Natural Language :: English
Classifier: Natural Language :: Esperanto
Classifier: Operating System :: OS Independent
Classifier: Programming Language :: Python
Classifier: Topic :: Education
Classifier: Topic :: Software Development
